TalkGTTS/__init__.py
TalkGTTS/other_module.py
TalkGTTS-0.3.dist-info/LICENSE
TalkGTTS-0.3.dist-info/METADATA
TalkGTTS-0.3.dist-info/WHEEL
TalkGTTS-0.3.dist-info/top_level.txt
TalkGTTS-0.3.dist-info/RECORD
