Metadata-Version: 2.1
Name: TalkGTTS
Version: 0.3
Summary: Uses GTTS to make it talk.
Home-page: https://github.com/Talklet123/Talk-Module
Author: Talklet123
Author-email: developer1234567890234@yahoo.com
License: MIT
Platform: UNKNOWN
License-File: LICENSE
Requires-Dist: gTTS (>=2.4.0)
Requires-Dist: pygame (>=2.5.2)
